qdollar/Point.py
qdollar/__init__.py
qdollar/gesture.py
qdollar/recognizer.py
qdollar-0.0.2.dist-info/LICENSE
qdollar-0.0.2.dist-info/METADATA
qdollar-0.0.2.dist-info/WHEEL
qdollar-0.0.2.dist-info/top_level.txt
qdollar-0.0.2.dist-info/RECORD
