Metadata-Version: 2.1
Name: qdollar
Version: 0.0.2
Summary: qdollar is the Python Implementation of $Q Super-Quick Recognizer
Home-page: https://github.com/shakyaprashant/qdollar
Author: Prashant Shakya
Author-email: prashushakya@gmail.com
License: UNKNOWN
Platform: UNKNOWN
Classifier: Programming Language :: Python :: 3
Classifier: License :: OSI Approved :: GNU Lesser General Public License v3 (LGPLv3)
Classifier: Operating System :: OS Independent
Classifier: Development Status :: 4 - Beta
Classifier: Intended Audience :: Developers
Classifier: Natural Language :: English
Classifier: Topic :: Scientific/Engineering :: Human Machine Interfaces
Classifier: Topic :: Software Development :: Libraries :: Python Modules
